quickbars_bridge/__init__.py
quickbars_bridge/client.py
quickbars_bridge/events.py
quickbars_bridge/hass_flow.py
quickbars_bridge/hass_helpers.py
quickbars_bridge/qb.py
quickbars_bridge-0.0.6.dist-info/METADATA
quickbars_bridge-0.0.6.dist-info/WHEEL
quickbars_bridge-0.0.6.dist-info/licenses/LICENSE
quickbars_bridge-0.0.6.dist-info/RECORD
