Metadata-Version: 2.4
Name: quickbars-bridge
Version: 0.0.6
Summary: Async client for QuickBars TV app
Project-URL: Homepage, https://github.com/trooped/quickbars-bridge
Project-URL: Issues, https://github.com/trooped/quickbars-bridge/issues
License: MIT
License-File: LICENSE
Requires-Python: >=3.11
Requires-Dist: aiohttp>=3.9.0
